network_pipeline/__init__.py
network_pipeline/build_packet_key.py
network_pipeline/build_training_request.py
network_pipeline/connect_forwarder.py
network_pipeline/consts.py
network_pipeline/convert_pkt_to_json.py
network_pipeline/create_layer_2_socket.py
network_pipeline/handle_packets.py
network_pipeline/network_packet_task.py
network_pipeline/parse_network_data.py
network_pipeline/publisher.py
network_pipeline/record_packets_to_csv.py
network_pipeline/shutdown_consumers.py
network_pipeline/simulated_work_task.py
network_pipeline/start_consumers_for_queue.py
network_pipeline/utils.py
network_pipeline/worker_to_process_packets.py
network_pipeline/log/__init__.py
network_pipeline/log/setup_logging.py
network_pipeline/scripts/__init__.py
network_pipeline/scripts/arp_send_msg.py
network_pipeline/scripts/base_capture.py
network_pipeline/scripts/capture_arp.py
network_pipeline/scripts/capture_icmp.py
network_pipeline/scripts/capture_ssh.py
network_pipeline/scripts/capture_tcp.py
network_pipeline/scripts/capture_telnet.py
network_pipeline/scripts/capture_udp.py
network_pipeline/scripts/consolidate_packets.py
network_pipeline/scripts/icmp_send_msg.py
network_pipeline/scripts/listen_tcp_port.py
network_pipeline/scripts/listen_udp_port.py
network_pipeline/scripts/network_agent.py
network_pipeline/scripts/packets_rabbitmq.py
network_pipeline/scripts/packets_redis.py
network_pipeline/scripts/tcp_send_large_msg.py
network_pipeline/scripts/tcp_send_msg.py
network_pipeline/scripts/udp_send_msg.py
network_pipeline/scripts/builders/__init__.py
network_pipeline/scripts/builders/prepare_dataset.py
network_pipeline/scripts/modelers/__init__.py
network_pipeline/scripts/modelers/keras_dnn.py
network_pipeline/scripts/tools/__init__.py
network_pipeline/scripts/tools/arp_send_msg.py
network_pipeline-1.2.11.data/scripts/arp_send_msg.py
network_pipeline-1.2.11.data/scripts/capture_arp.py
network_pipeline-1.2.11.data/scripts/capture_icmp.py
network_pipeline-1.2.11.dist-info/LICENSE
network_pipeline-1.2.11.dist-info/METADATA
network_pipeline-1.2.11.dist-info/WHEEL
network_pipeline-1.2.11.dist-info/top_level.txt
network_pipeline-1.2.11.dist-info/RECORD
