Metadata-Version: 2.1
Name: network-pipeline
Version: 1.2.11
Summary: Distributed Network Packet Analysis Pipeline for Layer 2, 3 and 4 Frames
Home-page: https://github.com/jay-johnson/network-pipeline
Author: Jay Johnson
Author-email: jay.p.h.johnson@gmail.com
License: UNKNOWN
Platform: UNKNOWN
Classifier: Development Status :: 5 - Production/Stable
Classifier: Intended Audience :: Developers
Classifier: License :: OSI Approved :: Apache Software License
Classifier: Operating System :: OS Independent
Classifier: Programming Language :: Python :: 3.5
Classifier: Programming Language :: Python :: 3.6
Classifier: Programming Language :: Python :: Implementation :: PyPy
Classifier: Topic :: Software Development :: Libraries :: Python Modules
Requires-Dist: antinex-client
Requires-Dist: ansible (>=1.9)
Requires-Dist: celery-connectors
Requires-Dist: coverage
Requires-Dist: colorlog
Requires-Dist: flake8
Requires-Dist: future
Requires-Dist: kamene
Requires-Dist: netifaces
Requires-Dist: pandas
Requires-Dist: pep8
Requires-Dist: pipenv
Requires-Dist: pydocstyle
Requires-Dist: pycodestyle
Requires-Dist: pylint
Requires-Dist: python-logstash
Requires-Dist: python-owasp-zap-v2.4
Requires-Dist: python-dateutil (<2.7.0)
Requires-Dist: spylunking
Requires-Dist: tox
Requires-Dist: unittest2
Requires-Dist: mock
